opentelemetry_resourcedetector_kubernetes/__init__.py
opentelemetry_resourcedetector_kubernetes/py.typed
opentelemetry_resourcedetector_kubernetes-0.3.0.dist-info/LICENSE
opentelemetry_resourcedetector_kubernetes-0.3.0.dist-info/METADATA
opentelemetry_resourcedetector_kubernetes-0.3.0.dist-info/WHEEL
opentelemetry_resourcedetector_kubernetes-0.3.0.dist-info/top_level.txt
opentelemetry_resourcedetector_kubernetes-0.3.0.dist-info/RECORD
