Metadata-Version: 2.1
Name: opentelemetry-resourcedetector-kubernetes
Version: 0.3.0
Summary: An OpenTelemetry package to populates Resource attributes for Kubernetes pods
Home-page: https://github.com/chrisguidry/opentelemetry-resourcedetector-kubernetes
Author: Chris Guidry
Author-email: chris@theguidrys.us
Project-URL: Bug Tracker, https://github.com/chrisguidry/opentelemetry-resourcedetector-kubernetes/issues
Classifier: Programming Language :: Python :: 3
Classifier: License :: OSI Approved :: MIT License
Requires-Python: >=3.8
Provides-Extra: dev
License-File: LICENSE
